agi_med_common/__init__.py
agi_med_common/api.py
agi_med_common/file_storage.py
agi_med_common/parallel_map.py
agi_med_common/type_union.py
agi_med_common/utils.py
agi_med_common/validators.py
agi_med_common/xml_parser.py
agi_med_common/models/__init__.py
agi_med_common/models/base.py
agi_med_common/models/chat.py
agi_med_common/models/chat_item.py
agi_med_common/models/enums.py
agi_med_common/models/tracks.py
agi_med_common/models/widget.py
agi_med_common/models/base_config_models/__init__.py
agi_med_common/models/base_config_models/gigachat_config.py
agi_med_common-5.2.4.dist-info/METADATA
agi_med_common-5.2.4.dist-info/WHEEL
agi_med_common-5.2.4.dist-info/top_level.txt
agi_med_common-5.2.4.dist-info/RECORD
